transcriber/__init__.py
transcriber/__main__.py
transcriber/audio_io.py
transcriber/config.py
transcriber/getting_session.py
transcriber/paths.py
transcriber/summarizer.py
transcriber/websocket_client.py
transcriber_sh-0.1.2.dist-info/METADATA
transcriber_sh-0.1.2.dist-info/WHEEL
transcriber_sh-0.1.2.dist-info/entry_points.txt
transcriber_sh-0.1.2.dist-info/top_level.txt
transcriber_sh-0.1.2.dist-info/RECORD
