Metadata-Version: 2.4
Name: transcriber-sh
Version: 0.1.2
Summary: Real-time microphone → OpenAI → text (CLI)
Author-email: Your Name <you@example.com>
Requires-Python: >=3.9
Requires-Dist: certifi==2025.4.26
Requires-Dist: cffi==1.17.1
Requires-Dist: charset-normalizer==3.4.2
Requires-Dist: dotenv==0.9.9
Requires-Dist: idna==3.10
Requires-Dist: numpy==1.26.3
Requires-Dist: pycparser==2.22
Requires-Dist: python-dotenv==1.1.0
Requires-Dist: requests==2.32.4
Requires-Dist: soundcard==0.4.4
Requires-Dist: urllib3==2.4.0
Requires-Dist: websocket-client==1.8.0
Provides-Extra: dev
Requires-Dist: pytest>=8.2; extra == "dev"
Requires-Dist: ruff>=0.4; extra == "dev"
